asynccore/__init__.py
asynccore/__main__.py
asynccore/activity.py
asynccore/cache.py
asynccore/client.py
asynccore/components.py
asynccore/enums.py
asynccore/errors.py
asynccore/http.py
asynccore/logger.py
asynccore/permissionbuilder.py
asynccore/tasks.py
asynccore/typings.py
asynccore/user.py
asynccore/commands/__init__.py
asynccore/commands/application.py
asynccore/commands/slashcommands.py
asynccore/gateway/__init__.py
asynccore/gateway/enums.py
asynccore/gateway/errors.py
asynccore/gateway/event.py
asynccore/gateway/gateway.py
asynccore/gateway/response.py
asynccore-1.2.1.dist-info/LICENSE
asynccore-1.2.1.dist-info/METADATA
asynccore-1.2.1.dist-info/WHEEL
asynccore-1.2.1.dist-info/top_level.txt
asynccore-1.2.1.dist-info/RECORD
